khapi/__init__.py
khapi/admin.py
khapi/api_core.py
khapi/apps.py
khapi/exceptions.py
khapi/khapi_middleware.py
khapi/khapi_start.py
khapi/methods.py
khapi/models.py
khapi/tests.py
khapi/views.py
khapi/auth_system/__init__.py
khapi/auth_system/admin.py
khapi/auth_system/apps.py
khapi/auth_system/auth_core.py
khapi/auth_system/models.py
khapi/auth_system/permissions.py
khapi/auth_system/tests.py
khapi/auth_system/views.py
khapi/auth_system/migrations/__init__.py
khapi/cache_system/cache_models.py
khapi/cache_system/check_data_type.py
khapi/cache_system/core.py
khapi/cache_system/create.py
khapi/cache_system/dict_manager.py
khapi/cache_system/hash.py
khapi/cache_system/store_update.py
khapi/cache_system/token_permission.py
khapi/management/commands/khapi.py
khapi/migrations/__init__.py
khapi-0.9.0.dist-info/METADATA
khapi-0.9.0.dist-info/WHEEL
khapi-0.9.0.dist-info/licenses/LICENSE
khapi-0.9.0.dist-info/RECORD
