Metadata-Version: 2.1
Name: khapi
Version: 0.9.0
Summary: A powerful Django app for creating APIs.
Project-URL: Homepage, https://github.com/khfix/django-khapi
Project-URL: Issues, https://github.com/khfix/django-khapi/issues
Author-email: khfix <hamza.alkhatib.se@gmail.com>
License-File: LICENSE
Classifier: License :: OSI Approved :: MIT License
Classifier: Operating System :: OS Independent
Classifier: Programming Language :: Python :: 3
Requires-Python: >=3.6
